streamlit_analytics/__init__.py
streamlit_analytics/display.py
streamlit_analytics/firestore.py
streamlit_analytics/main.py
streamlit_analytics/utils.py
streamlit_analytics-0.4.1.dist-info/LICENSE
streamlit_analytics-0.4.1.dist-info/METADATA
streamlit_analytics-0.4.1.dist-info/WHEEL
streamlit_analytics-0.4.1.dist-info/top_level.txt
streamlit_analytics-0.4.1.dist-info/RECORD
