Metadata-Version: 2.1
Name: streamlit-analytics
Version: 0.4.1
Summary: Track & visualize user interactions with your streamlit app
Home-page: https://github.com/jrieke/streamlit-analytics
Author: Johannes Rieke
Author-email: johannes.rieke@gmail.com
License: MIT
Classifier: Programming Language :: Python :: 3
Classifier: Programming Language :: Python :: 3.6
Classifier: Programming Language :: Python :: 3.7
Classifier: Programming Language :: Python :: 3.8
Classifier: Operating System :: OS Independent
Classifier: License :: OSI Approved :: MIT License
Classifier: Intended Audience :: Developers
Requires-Python: >=3.6
License-File: LICENSE
